click_config_file.py
click_config_file-0.5.0.dist-info/LICENSE
click_config_file-0.5.0.dist-info/METADATA
click_config_file-0.5.0.dist-info/WHEEL
click_config_file-0.5.0.dist-info/top_level.txt
click_config_file-0.5.0.dist-info/RECORD
