Metadata-Version: 2.1
Name: click-config-file
Version: 0.5.0
Summary: Configuration file support for click applications.
Home-page: http://github.com/phha/click_config_file
Author: Philipp Hack
Author-email: philipp.hack@gmail.com
License: MIT
Platform: UNKNOWN
Classifier: Development Status :: 4 - Beta
Classifier: Intended Audience :: Developers
Classifier: License :: OSI Approved :: MIT License
Classifier: Programming Language :: Python
Classifier: Programming Language :: Python :: 3
Requires-Dist: click (>=6.7)
Requires-Dist: configobj (>=5.0.6)
